core_graph/__init__.py
core_graph/func.py
core_graph/pipeline_ig.py
core_graph/pipeline_nx.py
core_graph/plot_interactive.py
core_graph-0.0.6.dist-info/METADATA
core_graph-0.0.6.dist-info/WHEEL
core_graph-0.0.6.dist-info/licenses/LICENSE
core_graph-0.0.6.dist-info/RECORD
