Metadata-Version: 2.3
Name: core_graph
Version: 0.0.6
Summary: A utility package for data science
Project-URL: Homepage, https://github.com/kevinkhang2909/core_graph
Project-URL: Bug Tracker, https://github.com/kevinkhang2909/core_graph/issues
Author-email: Kevin Khang <kevinkhang2909@gmail.com>
License: Copyright (c) 2024 Kevin Khang
License-File: LICENSE
Keywords: api, google, aws
Classifier: License :: OSI Approved :: MIT License
Classifier: Operating System :: OS Independent
Classifier: Programming Language :: Python :: 3
Requires-Python: >=3.11
Requires-Dist: igraph
Requires-Dist: infomap
Requires-Dist: matplotlib
Requires-Dist: networkx
Requires-Dist: numpy
Requires-Dist: polars
Requires-Dist: tqdm
